CyroWebB/Request.py
CyroWebB/Response.py
CyroWebB/__init__.py
CyroWebB/frontend_endpoints.py
CyroWebB/render.py
CyroWebB/Plugins/Database.py
CyroWebB/Plugins/__init__.py
CyroWebB/Plugins/base.py
CyroWebB/Production/__init__.py
CyroWebB-0.0.6.1.dist-info/LICENSE
CyroWebB-0.0.6.1.dist-info/METADATA
CyroWebB-0.0.6.1.dist-info/WHEEL
CyroWebB-0.0.6.1.dist-info/entry_points.txt
CyroWebB-0.0.6.1.dist-info/top_level.txt
CyroWebB-0.0.6.1.dist-info/RECORD
