Metadata-Version: 2.1
Name: CyroWebB
Version: 0.0.6.1
Summary: Backend Framework To Go Together With CyroWebF Frontend Framework.
Home-page: https://github.com/CyroCoders/CyroWebB
Author: CyroCoders
Author-email: pypi@cyrocoders.ml
License: UNKNOWN
Project-URL: Bug Tracker, https://github.com/CyroCoders/CyroWebB/issues
Platform: UNKNOWN
Classifier: Programming Language :: Python :: 3
Classifier: License :: OSI Approved :: MIT License
Classifier: Operating System :: OS Independent
Requires-Python: >=3
License-File: LICENSE
Requires-Dist: Jinja2 (==2.11.2)
Requires-Dist: Brotli (==1.0.9)
Requires-Dist: WebOb (==1.8.7)
Requires-Dist: parse (==1.19.0)
Requires-Dist: psutil (==5.8.0)
